README.rst
setup.cfg
setup.py
./__init__.py
./configuration.py
./configuration.xml
./payment.py
./payment.xml
./sale.py
./sale.xml
./tryton.cfg
./locale/de_DE.po
./locale/fr_FR.po
./tests/__init__.py
./tests/test_sale.py
./tests/test_views_depends.py
./view/configuration_form.xml
./view/sale_form.xml
./view/sale_payment_add_form.xml
./view/sale_payment_form.xml
./view/sale_payment_tree.xml
openlabs_sale_payment_gateway.egg-info/PKG-INFO
openlabs_sale_payment_gateway.egg-info/SOURCES.txt
openlabs_sale_payment_gateway.egg-info/dependency_links.txt
openlabs_sale_payment_gateway.egg-info/entry_points.txt
openlabs_sale_payment_gateway.egg-info/not-zip-safe
openlabs_sale_payment_gateway.egg-info/requires.txt
openlabs_sale_payment_gateway.egg-info/top_level.txt